bda/plone/prometheusexporter/__init__.py
bda/plone/prometheusexporter/configure.zcml
bda/plone/prometheusexporter/interfaces.py
bda/plone/prometheusexporter/testing.py
bda/plone/prometheusexporter/view.py
bda/plone/prometheusexporter/profiles/default/browserlayer.xml
bda/plone/prometheusexporter/profiles/default/metadata.xml
bda/plone/prometheusexporter/profiles/uninstall/browserlayer.xml
bda_plone_prometheusexporter-1.0a1.dist-info/METADATA
bda_plone_prometheusexporter-1.0a1.dist-info/WHEEL
bda_plone_prometheusexporter-1.0a1.dist-info/licenses/LICENSE.GPL
bda_plone_prometheusexporter-1.0a1.dist-info/licenses/LICENSE.md
bda_plone_prometheusexporter-1.0a1.dist-info/RECORD
