Metadata-Version: 2.3
Name: bda.plone.prometheusexporter
Version: 1.0a1
Summary: Prometheus Exporter for Plone and Zope
Project-URL: PyPI, https://pypi.python.org/pypi/bda.plone.prometheusexporter
Project-URL: Changelog, https://github.com/bluedynamics/bda.plone.prometheusexporter/blob/main/CHANGES.md
Project-URL: Source, https://github.com/bluedynamics/bda.plone.prometheusexporter
Project-URL: Issues, https://github.com/bluedynamics/bda.plone.prometheusexporter/issues
Author-email: Jens Klein <jk@kleinundpartner.at>
Maintainer-email: Jens Klein <jk@kleinundpartner.at>
License: GPL 2.0
License-File: LICENSE.GPL
License-File: LICENSE.md
Keywords: plone,prometheus
Classifier: Development Status :: 5 - Production/Stable
Classifier: Environment :: Web Environment
Classifier: Framework :: Plone
Classifier: License :: OSI Approved :: GNU General Public License v2 (GPLv2)
Classifier: Operating System :: OS Independent
Classifier: Programming Language :: Python
Classifier: Programming Language :: Python :: 3.11
Classifier: Programming Language :: Python :: 3.12
Requires-Python: >=3.11
Requires-Dist: products-cmfplone
Requires-Dist: prometheus-client
Provides-Extra: test
Requires-Dist: pdbpp; extra == 'test'
Requires-Dist: plone-app-robotframework; extra == 'test'
Requires-Dist: plone-app-testing; extra == 'test'
Requires-Dist: pytest-plone; extra == 'test'
